Metadata-Version: 1.0
Name: jli-dsnd-distributions
Version: 0.2
Summary: Gaussian and Binomial distributions
Home-page: UNKNOWN
Author: Haotong Li
Author-email: jamesli0512@gmail.com
License: UNKNOWN
Platform: UNKNOWN
